pycupscli/__init__.py
pycupscli/pycupscli.py
pycupscli-1.2.0.dist-info/LICENSE
pycupscli-1.2.0.dist-info/METADATA
pycupscli-1.2.0.dist-info/WHEEL
pycupscli-1.2.0.dist-info/entry_points.txt
pycupscli-1.2.0.dist-info/RECORD
