Metadata-Version: 2.1
Name: pycupscli
Version: 1.2.0
Summary: 
Author: Benoist Wolleb
Author-email: benoist.wolleb@la-cave.ch
Requires-Python: >=3.11,<4.0
Classifier: Programming Language :: Python :: 3
Classifier: Programming Language :: Python :: 3.11
Classifier: Programming Language :: Python :: 3.12
Requires-Dist: pycups (>=2.0.1,<3.0.0)
